{"commitInfo":{"timestamp":1783431502716,"operation":"WRITE","operationParameters":{"mode":"Overwrite","partitionBy":"[]"},"isolationLevel":"Serializable","isBlindAppend":false,"operationMetrics":{"numFiles":"1","numOutputRows":"298","numOutputBytes":"3987"},"engineInfo":"Apache-Spark/3.5.1 Delta-Lake/3.2.0","txnId":"92aa1ed3-b570-4ede-a868-f2fbde524655"}}
{"metaData":{"id":"05fdb01d-ed70-4469-9d72-1471f69561fd","format":{"provider":"parquet","options":{}},"schemaString":"{\"type\":\"struct\",\"fields\":[{\"name\":\"vehicle_id\",\"type\":\"string\",\"nullable\":true,\"metadata\":{}},{\"name\":\"vehicle_sk\",\"type\":\"long\",\"nullable\":true,\"metadata\":{}}]}","partitionColumns":[],"configuration":{},"createdTime":1783431497956}}
{"protocol":{"minReaderVersion":1,"minWriterVersion":2}}
{"add":{"path":"part-00000-3232022b-1063-4082-888d-484c2389e8ef-c000.snappy.parquet","partitionValues":{},"size":3987,"modificationTime":1783431501195,"dataChange":true,"stats":"{\"numRecords\":298,\"minValues\":{\"vehicle_id\":\"VEH-100\",\"vehicle_sk\":0},\"maxValues\":{\"vehicle_id\":\"VEH-997\",\"vehicle_sk\":297},\"nullCount\":{\"vehicle_id\":0,\"vehicle_sk\":0}}"}}
