{"commitInfo":{"timestamp":1783438234128,"operation":"WRITE","operationParameters":{"mode":"Overwrite","partitionBy":"[]"},"readVersion":1,"isolationLevel":"Serializable","isBlindAppend":false,"operationMetrics":{"numFiles":"1","numOutputRows":"3","numOutputBytes":"1829"},"engineInfo":"Apache-Spark/3.5.1 Delta-Lake/3.2.0","txnId":"59e019a1-087e-4a3b-bb4f-9478a8345152"}}
{"add":{"path":"part-00000-ba3ab9f8-4e0e-4223-9ff4-e2acc6dad399-c000.snappy.parquet","partitionValues":{},"size":1829,"modificationTime":1783438232520,"dataChange":true,"stats":"{\"numRecords\":3,\"minValues\":{\"event_date\":\"2026-07-06\",\"year\":2026,\"month\":7,\"day\":6,\"hour\":12,\"date_sk\":0},\"maxValues\":{\"event_date\":\"2026-07-07\",\"year\":2026,\"month\":7,\"day\":7,\"hour\":13,\"date_sk\":2},\"nullCount\":{\"event_date\":0,\"year\":0,\"month\":0,\"day\":0,\"hour\":0,\"date_sk\":0}}"}}
{"remove":{"path":"part-00000-02924acb-6c27-440a-8e65-a6b923fc55cf-c000.snappy.parquet","deletionTimestamp":1783438234127,"dataChange":true,"extendedFileMetadata":true,"partitionValues":{},"size":1829}}
